setup.py
yorbay/__init__.py
yorbay/builder.py
yorbay/compiler.py
yorbay/context.py
yorbay/discovery.py
yorbay/exceptions.py
yorbay/globals.py
yorbay/lang.py
yorbay/loader.py
yorbay/parser.py
yorbay/syntax.py
yorbay.egg-info/PKG-INFO
yorbay.egg-info/SOURCES.txt
yorbay.egg-info/dependency_links.txt
yorbay.egg-info/top_level.txt
yorbay/debug/__init__.py
yorbay/debug/compiler.py
yorbay/debug/parser.py
yorbay/debug/similarity.py
yorbay/debug/stacktrace.py