Metadata-Version: 1.1
Name: yorbay
Version: 0.1.dev1
Summary: Localization framework based on l20n file format
Home-page: https://github.com/rusek/yorbay-python
Author: Krzysztof Rusek
Author-email: savix5@gmail.com
License: Apache License, Version 2.0
Keywords: localization
Platform: UNKNOWN
Classifier: Development Status :: 1 - Planning
Classifier: Intended Audience :: Developers
Classifier: License :: OSI Approved :: Apache Software License
Classifier: Operating System :: OS Independent
Classifier: Programming Language :: Python
Classifier: Programming Language :: Python :: 2
Classifier: Programming Language :: Python :: 2.6
Classifier: Programming Language :: Python :: 2.7
Classifier: Topic :: Software Development :: Internationalization
